{"modelEntity":{"id":"48D9021B-805D-40C8-AE40-5CAC02947174","preferredFilename":"","createdDate":"2024-03-03T04:57:58Z","version":"1.0","modifiedDate":"2024-03-03T04:57:58Z","experimentID":"9305249A-BCA2-499C-904F-1D06111C46E2","title":"","modelURL":"Models\/ClickjackingDetection_v5.mlmodel"},"id":"9305249A-BCA2-499C-904F-1D06111C46E2","title":"ClickjackingDetection 4","evaluationEntity":{"id":"eabeeafb-13ae-4754-abeb-4c569afd5f74","dataResult":{},"analysedDataType":"none"},"version":"1.0","contentDataResult":{"createdDate":"2024-03-03T04:57:58Z"},"activityEntities":["experimentCreated",[{"id":"4C484863-CA73-488B-A15F-BB776928C5C8","title":"Model Source Created","subtitle":"ClickjackingDetection_v5","createdDate":"2024-03-03T04:57:58Z","event":"experimentCreated"}],"trainingDataAdded",[{"subtitle":"ClickjackingTraining","event":"trainingDataAdded","title":"Training Data Added","id":"2443933B-0618-48E3-9507-6CFB767C5E2C","createdDate":"2024-03-03T04:58:02Z"}],"evaluationStarted",[{"subtitle":"ClickjackingDetection_v5","title":"Testing Started","createdDate":"2024-03-03T05:03:12Z","id":"865003C6-AA09-47AE-ACDA-70BEE74F108C","event":"evaluationStarted"},{"createdDate":"2024-03-03T05:04:11Z","subtitle":"ClickjackingDetection_v5","id":"37BFBA72-B062-4E7D-AE28-894960210709","event":"evaluationStarted","title":"Testing Started"},{"createdDate":"2024-03-04T04:44:52Z","id":"A48FEB1D-493D-4245-A80C-4E749E3EFF09","title":"Testing Started","subtitle":"ClickjackingDetection_v5","event":"evaluationStarted"}],"trainingStarted",[{"subtitle":"75 iterations","event":"trainingStarted","title":"Training Started","id":"0A6BBA82-465D-46EF-B5A4-4E9C7C1137E6","createdDate":"2024-03-03T04:58:54Z"}],"evaluationFinished",[{"event":"evaluationFinished","title":"Testing Completed","subtitle":"ClickjackingDetection_v5","createdDate":"2024-03-03T05:03:13Z","id":"321E73CC-E597-499E-8E72-BD76796E8361"},{"createdDate":"2024-03-03T05:04:12Z","id":"230DC454-34B1-467A-B6DA-2300208B9B72","event":"evaluationFinished","title":"Testing Completed","subtitle":"ClickjackingDetection_v5"},{"subtitle":"ClickjackingDetection_v5","id":"7010D390-E6EA-4DD8-BCD1-3CB08C660E79","event":"evaluationFinished","title":"Testing Completed","createdDate":"2024-03-04T04:44:53Z"}],"trainingFinished",[{"id":"57C5A3F7-D3BE-4B85-B691-5541584F3496","title":"Training Completed","subtitle":"75 iterations","createdDate":"2024-03-03T05:03:10Z","event":"trainingFinished"}]],"snapshotRole":{"withoutSnapshots":0},"settingEntity":{"handActionClassifierAugmentations":[],"iterationCount":75,"algorithmType":"maxEnt","odAlgorithmType":"darknetYolo","seedType":"default","odGridHeight":13,"styleTransferAlgorithmType":"image","harVideoAugmentations":0,"handPoseClassifierAugmentations":[],"featureNames":[],"odGridWidth":13,"augmentations":[],"transferLearningEmbeddingType":"dynamic","recommendedIterationCount":2000,"taskType":"objectDetector"},"state":"trained","trainingEntity":{"startTime":"2024-03-03T04:58:54Z","analysedDataType":"datasource","trainingResults":{"objectDetector":{"averagePrecision":{"normal":{"variedIoU":0.059491951018571854,"IoU50":0.21910226345062256},"clickjacking":{"variedIoU":0.13451364636421204,"IoU50":0.510581374168396}},"meanAveragePrecision":{"IoU50":0.3648418188095093,"variedIoU":0.0970027968287468}}},"snapshottableCheckpoints":{"75":{"createdDate":"2024-03-03T05:03:06Z","iteration":75,"modelURL":"file:\/\/\/Users\/aniavetian\/Library\/Caches\/com.apple.dt.createml\/projects\/E17F6008-3C8A-403E-8EFC-E0619E49FAB7325448107e421ef65685cb4b4c7c25fd260c408d\/sessions\/checkpoint.sessions\/9305249A-BCA2-499C-904F-1D06111C46E2\/training-000000075.checkpoint.model\/checkpointModel.mlmodel"}},"resumableCheckpointURL":"Checkpoints\/9305249A-BCA2-499C-904F-1D06111C46E2.ClickjackingDetection_v5.checkpoint","resumableCheckpoint":{"iteration":75,"createdDate":"2024-03-03T05:03:06Z","checkpointURL":"file:\/\/\/Users\/aniavetian\/Library\/Caches\/com.apple.dt.createml\/projects\/E17F6008-3C8A-403E-8EFC-E0619E49FAB7325448107e421ef65685cb4b4c7c25fd260c408d\/sessions\/checkpoint.sessions\/9305249A-BCA2-499C-904F-1D06111C46E2\/training-000000075.checkpoint"},"snapshottableCheckpointModelURL":"Checkpoints\/9305249A-BCA2-499C-904F-1D06111C46E2.ClickjackingDetection_v5.checkpoint\/training-000000075.checkpoint.model\/checkpointModel.mlmodel","validationAccuracy":0.2868156433105469,"validationResults":{"objectDetector":{"averagePrecision":{"normal":{"variedIoU":0.02951851859688759,"IoU50":0.11185184866189957},"clickjacking":{"variedIoU":0.10713032633066177,"IoU50":0.4617794454097748}},"meanAveragePrecision":{"variedIoU":0.06832442432641983,"IoU50":0.2868156433105469}}},"trainingAccuracy":0.3648418188095093,"progress":[{"currentRowIndex":0,"percentComplete":0,"isLast":false,"tableDone":false,"count":1,"tableIndex":0,"odColumnHeader":{"loss":5.403831481933594,"iterationCount":1,"elapsedTime":8.739109}},{"tableIndex":0,"count":2,"tableDone":false,"isLast":false,"odColumnHeader":{"elapsedTime":12.216132,"iterationCount":2,"loss":5.301768779754639},"currentRowIndex":0,"percentComplete":0},{"tableDone":false,"odColumnHeader":{"loss":5.243625640869141,"iterationCount":3,"elapsedTime":16.244237},"tableIndex":0,"isLast":false,"currentRowIndex":0,"percentComplete":0,"count":3},{"count":4,"odColumnHeader":{"elapsedTime":19.773187,"iterationCount":4,"loss":5.221554756164551},"tableDone":false,"currentRowIndex":0,"isLast":false,"percentComplete":0,"tableIndex":0},{"percentComplete":0,"tableIndex":0,"odColumnHeader":{"loss":5.2063374519348145,"iterationCount":5,"elapsedTime":19.773365},"currentRowIndex":0,"count":5,"isLast":false,"tableDone":false},{"percentComplete":0,"count":10,"isLast":false,"tableIndex":0,"tableDone":false,"odColumnHeader":{"loss":5.0119099617004395,"elapsedTime":0,"iterationCount":10},"currentRowIndex":0},{"isLast":false,"percentComplete":0,"count":15,"tableDone":false,"odColumnHeader":{"iterationCount":15,"loss":4.8824639320373535,"elapsedTime":54.110308},"currentRowIndex":0,"tableIndex":0},{"odColumnHeader":{"iterationCount":20,"loss":4.719753265380859,"elapsedTime":0},"tableDone":false,"percentComplete":0,"tableIndex":0,"currentRowIndex":0,"count":20,"isLast":false},{"tableDone":false,"odColumnHeader":{"elapsedTime":86.709943,"iterationCount":25,"loss":4.644326686859131},"tableIndex":0,"isLast":false,"percentComplete":0,"currentRowIndex":0,"count":25},{"tableDone":false,"isLast":false,"tableIndex":0,"odColumnHeader":{"iterationCount":30,"loss":4.365609645843506,"elapsedTime":0},"count":30,"currentRowIndex":0,"percentComplete":0},{"tableIndex":0,"percentComplete":0,"count":35,"isLast":false,"currentRowIndex":0,"tableDone":false,"odColumnHeader":{"elapsedTime":123.638055,"loss":4.26359748840332,"iterationCount":35}},{"percentComplete":0,"count":40,"isLast":false,"tableDone":false,"odColumnHeader":{"elapsedTime":0,"loss":4.059775352478027,"iterationCount":40},"currentRowIndex":0,"tableIndex":0},{"odColumnHeader":{"iterationCount":45,"loss":3.859057664871216,"elapsedTime":158.112241},"tableDone":false,"count":45,"tableIndex":0,"currentRowIndex":0,"percentComplete":0,"isLast":false},{"isLast":false,"percentComplete":0,"tableIndex":0,"currentRowIndex":0,"tableDone":false,"count":50,"odColumnHeader":{"loss":3.945626735687256,"elapsedTime":0,"iterationCount":50}},{"count":55,"isLast":false,"currentRowIndex":0,"tableIndex":0,"tableDone":false,"percentComplete":0,"odColumnHeader":{"iterationCount":55,"loss":3.9243569374084473,"elapsedTime":188.332481}},{"isLast":false,"tableDone":false,"currentRowIndex":0,"percentComplete":0,"count":60,"tableIndex":0,"odColumnHeader":{"iterationCount":60,"loss":3.7929768562316895,"elapsedTime":0}},{"currentRowIndex":0,"count":65,"tableIndex":0,"isLast":false,"percentComplete":0,"odColumnHeader":{"elapsedTime":220.061535,"loss":3.70169997215271,"iterationCount":65},"tableDone":false},{"count":70,"isLast":false,"tableIndex":0,"odColumnHeader":{"loss":3.7064783573150635,"elapsedTime":0,"iterationCount":70},"tableDone":false,"currentRowIndex":0,"percentComplete":0},{"tableIndex":0,"count":75,"currentRowIndex":0,"isLast":false,"tableDone":true,"odColumnHeader":{"loss":3.5053458213806152,"elapsedTime":251.055875,"iterationCount":75},"percentComplete":0}],"dataSourceID":"9A5C8A86-3DCE-4325-B076-16CEEDB300A8","checkpointMetrics":{"20":{"iteration":20,"createdDate":"2024-03-03T05:00:05Z","metrics":{"loss":4.719753265380859}},"40":{"createdDate":"2024-03-03T05:01:17Z","metrics":{"loss":4.059775352478027},"iteration":40},"50":{"metrics":{"loss":3.945626735687256},"createdDate":"2024-03-03T05:01:48Z","iteration":50},"75":{"createdDate":"2024-03-03T05:03:06Z","metrics":{"loss":3.5053458213806152},"iteration":75},"70":{"createdDate":"2024-03-03T05:02:51Z","iteration":70,"metrics":{"loss":3.7064783573150635}},"60":{"metrics":{"loss":3.7929768562316895},"createdDate":"2024-03-03T05:02:19Z","iteration":60},"30":{"iteration":30,"createdDate":"2024-03-03T05:00:41Z","metrics":{"loss":4.365609645843506}},"10":{"iteration":10,"metrics":{"loss":5.0119099617004395},"createdDate":"2024-03-03T04:59:33Z"}},"featureExtractionCheckpointMayBeAvailable":false,"dataResult":{"dataSourceID":"9A5C8A86-3DCE-4325-B076-16CEEDB300A8","itemsCount":50,"dataURL":"file:\/\/\/Users\/aniavetian\/Desktop\/School%20Work\/UWB\/Masters\/CSS539\/ARShield\/ClickjackingTraining\/","createdDate":"2024-03-03T04:57:58Z","classesCount":2,"dataAnalysis":{"issues":[{"description":"2 classes found, including clickjacking, normal","severity":"debug"},{"description":"56 annotations found, automatically creating validation set","severity":"good"},{"severity":"debug","description":"Smallest class is \"normal\" with 24 images"},{"description":"Largest class is \"clickjacking\" with 32 images","severity":"debug"}],"classifierAnalysis":{"labelStats":{"clickjacking":32,"normal":24}},"summary":{"counterExamples":0,"sampleCount":50,"canUseValidation":1,"classCount":2,"suggestedMaxIterations":2000}}},"finishTime":"2024-03-03T05:03:10Z"},"preferredFilename":"ClickjackingDetection_v5","modifiedDate":"2024-03-05T01:56:33Z","validationEntity":{"analysedDataType":"auto","dataResult":{"createdDate":"2024-03-03T04:57:58Z"}},"evaluationContainerEntity":{"id":"f43b75f5-1e5f-4281-8004-07324a45c859","previewType":"objectDetector","modifiedDate":"2024-03-05T01:56:33Z","validationEvaluationEntity":{"evaluationResult":{"objectDetector":{"meanAveragePrecision":{"variedIoU":0.06832442432641983,"IoU50":0.2868156433105469},"averagePrecision":{"normal":{"variedIoU":0.02951851859688759,"IoU50":0.11185184866189957},"clickjacking":{"variedIoU":0.10713032633066177,"IoU50":0.4617794454097748}}}},"id":"24f7d3d9-14e0-4216-bf84-2fab097f0451","createdDate":"2024-03-03T04:57:58Z","dataResult":{"createdDate":"2024-03-03T04:57:58Z"},"analysedDataType":"auto"},"testingEvaluationEntity":{"dataResult":{"createdDate":"2024-03-03T04:57:58Z","dataURL":"file:\/\/\/Users\/aniavetian\/Desktop\/School%20Work\/UWB\/Masters\/CSS539\/ARShield\/ClickjackingTesting\/","classesCount":2,"dataAnalysis":{"classifierAnalysis":{"labelStats":{"normal":2,"clickjacking":4}},"issues":[{"description":"2 classes found, including clickjacking, normal","severity":"debug"},{"severity":"warning","description":"Less than 50 total images found - add more to improve model validation"},{"severity":"debug","description":"Smallest class is \"normal\" with 2 images"},{"severity":"debug","description":"Largest class is \"clickjacking\" with 4 images"}],"summary":{"counterExamples":0,"sampleCount":6,"classCount":2,"suggestedMaxIterations":1000,"canUseValidation":0}},"dataSourceID":"4A3201E7-222C-4191-AA78-844D0461F88D","itemsCount":6},"id":"4ae7729a-3ae9-459e-9fd1-3b8e4df3fd41","dataSourceID":"4A3201E7-222C-4191-AA78-844D0461F88D","evaluationResult":{"objectDetector":{"meanAveragePrecision":{"variedIoU":0.09583333333333333,"IoU50":0.14583333333333334},"confusionMetrics":{"averagePrecision":{"IoU50":{"clickjacking":0.2916666666666667,"normal":0},"variedIoU":{"normal":0,"clickjacking":0.19166666666666665}},"isValid":true,"meanAveragePrecision":{"variedIoU":0.09583333333333333,"IoU50":0.14583333333333334}},"averagePrecision":{"clickjacking":{"variedIoU":0.19166666666666665,"IoU50":0.2916666666666667},"normal":{"variedIoU":0,"IoU50":0}},"rawDetails":[{"annotations":[{"coordinates":{"width":0.7359128937007874,"x":0.42022945374015747,"y":0.35359697060849304,"height":0.22754741628543734},"label":"clickjacking"}],"inferences":[{"classifications":[{"confidence":0.9993277,"identifier":"clickjacking"},{"confidence":0.0006723018,"identifier":"normal"}],"coordinates":{"height":0.349365234375,"width":0.5908203125,"y":0.364990234375,"x":0.487060546875}},{"coordinates":{"y":0.346435546875,"x":0.65625,"width":0.53369140625,"height":0.21826171875},"classifications":[{"identifier":"clickjacking","confidence":0.97658575},{"confidence":0.023414236,"identifier":"normal"}]},{"classifications":[{"identifier":"clickjacking","confidence":0.99670625},{"confidence":0.0032937396,"identifier":"normal"}],"coordinates":{"height":0.4619140625,"y":0.28759765625,"x":0.6416015625,"width":0.59423828125}},{"classifications":[{"confidence":0.9874672,"identifier":"clickjacking"},{"confidence":0.012532798,"identifier":"normal"}],"coordinates":{"height":0.385009765625,"width":0.6572265625,"x":0.49169921875,"y":0.5078125}},{"coordinates":{"width":0.716796875,"x":0.340087890625,"height":0.48876953125,"y":0.281982421875},"classifications":[{"identifier":"clickjacking","confidence":0.99109},{"confidence":0.008910001,"identifier":"normal"}]},{"coordinates":{"width":0.4755859375,"y":0.40966796875,"x":0.58056640625,"height":0.1748046875},"classifications":[{"identifier":"normal","confidence":0.9980298},{"confidence":0.0019701507,"identifier":"clickjacking"}]},{"coordinates":{"x":0.265380859375,"y":0.43017578125,"width":0.66943359375,"height":0.42578125},"classifications":[{"confidence":0.9792739,"identifier":"clickjacking"},{"identifier":"normal","confidence":0.020726109}]}],"imagePath":"\/Users\/aniavetian\/Desktop\/School Work\/UWB\/Masters\/CSS539\/ARShield\/ClickjackingTesting\/CJTest2.PNG"},{"inferences":[{"coordinates":{"width":0.5361328125,"y":0.5791015625,"height":0.210693359375,"x":0.65087890625},"classifications":[{"identifier":"clickjacking","confidence":0.9682409},{"confidence":0.03175909,"identifier":"normal"}]}],"imagePath":"\/Users\/aniavetian\/Desktop\/School Work\/UWB\/Masters\/CSS539\/ARShield\/ClickjackingTesting\/CJTest1.PNG","annotations":[{"coordinates":{"y":0.5781873793600449,"x":0.6245232529527559,"width":0.6015009842519684,"height":0.20140348909882477},"label":"clickjacking"}]},{"imagePath":"\/Users\/aniavetian\/Desktop\/School Work\/UWB\/Masters\/CSS539\/ARShield\/ClickjackingTesting\/CJTest3.PNG","annotations":[{"label":"clickjacking","coordinates":{"width":0.7121370570866141,"y":0.5039707551742317,"height":0.20618019357663983,"x":0.40869525098425197}}],"inferences":[{"classifications":[{"confidence":0.98034024,"identifier":"clickjacking"},{"confidence":0.019659761,"identifier":"normal"}],"coordinates":{"height":0.44140625,"x":0.493896484375,"y":0.51171875,"width":0.5869140625}}]},{"annotations":[{"coordinates":{"height":0.21026029531810683,"width":0.6461306594488189,"x":0.4229976624015748,"y":0.5291053192122583},"label":"normal"}],"inferences":[],"imagePath":"\/Users\/aniavetian\/Desktop\/School Work\/UWB\/Masters\/CSS539\/ARShield\/ClickjackingTesting\/NTest2.PNG"},{"imagePath":"\/Users\/aniavetian\/Desktop\/School Work\/UWB\/Masters\/CSS539\/ARShield\/ClickjackingTesting\/CJTest4.PNG","annotations":[{"coordinates":{"x":0.39983698326771655,"height":0.30725867225897524,"width":0.45564714566929126,"y":0.47317096275998705},"label":"clickjacking"}],"inferences":[]},{"annotations":[{"label":"normal","coordinates":{"width":0.6630474901574803,"y":0.4691121855920818,"x":0.49203371062992124,"height":0.20376340857298345}}],"inferences":[],"imagePath":"\/Users\/aniavetian\/Desktop\/School Work\/UWB\/Masters\/CSS539\/ARShield\/ClickjackingTesting\/NTest1.PNG"}]}},"finishTime":"2024-03-03T05:03:13Z","accuracy":0.14583333333333334,"startTime":"2024-03-03T05:03:12Z","analysedDataType":"datasource","createdDate":"2024-03-03T04:57:58Z"},"createdDate":"2024-03-05T01:56:33Z","evaluationEntities":[{"accuracy":0.14583333333333334,"id":"a6234456-0461-4145-b7c9-12f568c544e0","startTime":"2024-03-04T04:44:52Z","analysedDataType":"datasource","dataSourceID":"4A3201E7-222C-4191-AA78-844D0461F88D","createdDate":"2024-03-04T04:44:47Z","finishTime":"2024-03-04T04:44:53Z","evaluationResult":{"objectDetector":{"rawDetails":[{"inferences":[{"classifications":[{"identifier":"clickjacking","confidence":0.9682409},{"identifier":"normal","confidence":0.03175909}],"coordinates":{"x":0.65087890625,"y":0.5791015625,"height":0.210693359375,"width":0.5361328125}}],"imagePath":"\/Users\/aniavetian\/Desktop\/School Work\/UWB\/Masters\/CSS539\/ARShield\/ClickjackingTesting\/CJTest1.PNG","annotations":[{"coordinates":{"width":0.6015009842519684,"y":0.5781873793600449,"height":0.20140348909882477,"x":0.6245232529527559},"label":"clickjacking"}]},{"imagePath":"\/Users\/aniavetian\/Desktop\/School Work\/UWB\/Masters\/CSS539\/ARShield\/ClickjackingTesting\/CJTest3.PNG","inferences":[{"classifications":[{"confidence":0.98034024,"identifier":"clickjacking"},{"identifier":"normal","confidence":0.019659761}],"coordinates":{"y":0.51171875,"width":0.5869140625,"x":0.493896484375,"height":0.44140625}}],"annotations":[{"coordinates":{"x":0.40869525098425197,"width":0.7121370570866141,"y":0.5039707551742317,"height":0.20618019357663983},"label":"clickjacking"}]},{"imagePath":"\/Users\/aniavetian\/Desktop\/School Work\/UWB\/Masters\/CSS539\/ARShield\/ClickjackingTesting\/CJTest4.PNG","annotations":[{"coordinates":{"y":0.47317096275998705,"width":0.45564714566929126,"x":0.39983698326771655,"height":0.30725867225897524},"label":"clickjacking"}],"inferences":[]},{"imagePath":"\/Users\/aniavetian\/Desktop\/School Work\/UWB\/Masters\/CSS539\/ARShield\/ClickjackingTesting\/CJTest2.PNG","annotations":[{"coordinates":{"x":0.42022945374015747,"width":0.7359128937007874,"y":0.35359697060849304,"height":0.22754741628543734},"label":"clickjacking"}],"inferences":[{"coordinates":{"height":0.349365234375,"width":0.5908203125,"y":0.364990234375,"x":0.487060546875},"classifications":[{"confidence":0.9993277,"identifier":"clickjacking"},{"identifier":"normal","confidence":0.0006723018}]},{"classifications":[{"identifier":"clickjacking","confidence":0.97658575},{"confidence":0.023414236,"identifier":"normal"}],"coordinates":{"width":0.53369140625,"y":0.346435546875,"x":0.65625,"height":0.21826171875}},{"coordinates":{"width":0.59423828125,"x":0.6416015625,"y":0.28759765625,"height":0.4619140625},"classifications":[{"confidence":0.99670625,"identifier":"clickjacking"},{"identifier":"normal","confidence":0.0032937396}]},{"coordinates":{"y":0.5078125,"x":0.49169921875,"height":0.385009765625,"width":0.6572265625},"classifications":[{"identifier":"clickjacking","confidence":0.9874672},{"confidence":0.012532798,"identifier":"normal"}]},{"coordinates":{"x":0.340087890625,"y":0.281982421875,"width":0.716796875,"height":0.48876953125},"classifications":[{"confidence":0.99109,"identifier":"clickjacking"},{"confidence":0.008910001,"identifier":"normal"}]},{"classifications":[{"identifier":"normal","confidence":0.9980298},{"identifier":"clickjacking","confidence":0.0019701507}],"coordinates":{"y":0.40966796875,"x":0.58056640625,"height":0.1748046875,"width":0.4755859375}},{"coordinates":{"height":0.42578125,"width":0.66943359375,"x":0.265380859375,"y":0.43017578125},"classifications":[{"identifier":"clickjacking","confidence":0.9792739},{"confidence":0.020726109,"identifier":"normal"}]}]},{"imagePath":"\/Users\/aniavetian\/Desktop\/School Work\/UWB\/Masters\/CSS539\/ARShield\/ClickjackingTesting\/NTest1.PNG","inferences":[],"annotations":[{"label":"normal","coordinates":{"width":0.6630474901574803,"x":0.49203371062992124,"height":0.20376340857298345,"y":0.4691121855920818}}]},{"inferences":[],"annotations":[{"label":"normal","coordinates":{"y":0.5291053192122583,"height":0.21026029531810683,"width":0.6461306594488189,"x":0.4229976624015748}}],"imagePath":"\/Users\/aniavetian\/Desktop\/School Work\/UWB\/Masters\/CSS539\/ARShield\/ClickjackingTesting\/NTest2.PNG"}],"confusionMetrics":{"meanAveragePrecision":{"IoU50":0.14583333333333334,"variedIoU":0.09583333333333333},"isValid":true,"averagePrecision":{"variedIoU":{"clickjacking":0.19166666666666665,"normal":0},"IoU50":{"clickjacking":0.2916666666666667,"normal":0}}},"averagePrecision":{"clickjacking":{"variedIoU":0.19166666666666665,"IoU50":0.2916666666666667},"normal":{"variedIoU":0,"IoU50":0}},"meanAveragePrecision":{"IoU50":0.14583333333333334,"variedIoU":0.09583333333333333}}},"dataResult":{"createdDate":"2024-03-04T04:44:51Z","classesCount":2,"itemsCount":6,"dataSourceID":"4A3201E7-222C-4191-AA78-844D0461F88D","dataAnalysis":{"issues":[{"description":"2 classes found, including clickjacking, normal","severity":"debug"},{"description":"Less than 50 total images found - add more to improve model validation","severity":"warning"},{"description":"Smallest class is \"normal\" with 2 images","severity":"debug"},{"severity":"debug","description":"Largest class is \"clickjacking\" with 4 images"}],"summary":{"suggestedMaxIterations":1000,"sampleCount":6,"counterExamples":0,"canUseValidation":0,"classCount":2},"classifierAnalysis":{"labelStats":{"clickjacking":4,"normal":2}}},"dataURL":"file:\/\/\/Users\/aniavetian\/Desktop\/School%20Work\/UWB\/Masters\/CSS539\/ARShield\/ClickjackingTesting\/"}},{"finishTime":"2024-03-03T05:04:12Z","accuracy":0.14583333333333334,"evaluationResult":{"objectDetector":{"rawDetails":[{"inferences":[{"classifications":[{"identifier":"clickjacking","confidence":0.9993277},{"confidence":0.0006723018,"identifier":"normal"}],"coordinates":{"height":0.349365234375,"x":0.487060546875,"width":0.5908203125,"y":0.364990234375}},{"coordinates":{"y":0.346435546875,"width":0.53369140625,"height":0.21826171875,"x":0.65625},"classifications":[{"identifier":"clickjacking","confidence":0.97658575},{"identifier":"normal","confidence":0.023414236}]},{"coordinates":{"width":0.59423828125,"x":0.6416015625,"height":0.4619140625,"y":0.28759765625},"classifications":[{"confidence":0.99670625,"identifier":"clickjacking"},{"identifier":"normal","confidence":0.0032937396}]},{"coordinates":{"x":0.49169921875,"width":0.6572265625,"y":0.5078125,"height":0.385009765625},"classifications":[{"identifier":"clickjacking","confidence":0.9874672},{"confidence":0.012532798,"identifier":"normal"}]},{"classifications":[{"confidence":0.99109,"identifier":"clickjacking"},{"confidence":0.008910001,"identifier":"normal"}],"coordinates":{"width":0.716796875,"y":0.281982421875,"x":0.340087890625,"height":0.48876953125}},{"coordinates":{"y":0.40966796875,"height":0.1748046875,"x":0.58056640625,"width":0.4755859375},"classifications":[{"identifier":"normal","confidence":0.9980298},{"identifier":"clickjacking","confidence":0.0019701507}]},{"classifications":[{"identifier":"clickjacking","confidence":0.9792739},{"confidence":0.020726109,"identifier":"normal"}],"coordinates":{"width":0.66943359375,"x":0.265380859375,"y":0.43017578125,"height":0.42578125}}],"annotations":[{"label":"clickjacking","coordinates":{"y":0.35359697060849304,"x":0.42022945374015747,"height":0.22754741628543734,"width":0.7359128937007874}}],"imagePath":"\/Users\/aniavetian\/Desktop\/School Work\/UWB\/Masters\/CSS539\/ARShield\/ClickjackingTesting\/CJTest2.PNG"},{"annotations":[{"coordinates":{"y":0.5039707551742317,"width":0.7121370570866141,"height":0.20618019357663983,"x":0.40869525098425197},"label":"clickjacking"}],"imagePath":"\/Users\/aniavetian\/Desktop\/School Work\/UWB\/Masters\/CSS539\/ARShield\/ClickjackingTesting\/CJTest3.PNG","inferences":[{"coordinates":{"y":0.51171875,"width":0.5869140625,"x":0.493896484375,"height":0.44140625},"classifications":[{"confidence":0.98034024,"identifier":"clickjacking"},{"confidence":0.019659761,"identifier":"normal"}]}]},{"imagePath":"\/Users\/aniavetian\/Desktop\/School Work\/UWB\/Masters\/CSS539\/ARShield\/ClickjackingTesting\/NTest2.PNG","annotations":[{"coordinates":{"width":0.6461306594488189,"x":0.4229976624015748,"y":0.5291053192122583,"height":0.21026029531810683},"label":"normal"}],"inferences":[]},{"imagePath":"\/Users\/aniavetian\/Desktop\/School Work\/UWB\/Masters\/CSS539\/ARShield\/ClickjackingTesting\/CJTest4.PNG","annotations":[{"label":"clickjacking","coordinates":{"width":0.45564714566929126,"x":0.39983698326771655,"height":0.30725867225897524,"y":0.47317096275998705}}],"inferences":[]},{"annotations":[{"coordinates":{"y":0.4691121855920818,"height":0.20376340857298345,"width":0.6630474901574803,"x":0.49203371062992124},"label":"normal"}],"inferences":[],"imagePath":"\/Users\/aniavetian\/Desktop\/School Work\/UWB\/Masters\/CSS539\/ARShield\/ClickjackingTesting\/NTest1.PNG"},{"annotations":[{"label":"clickjacking","coordinates":{"x":0.6245232529527559,"width":0.6015009842519684,"y":0.5781873793600449,"height":0.20140348909882477}}],"imagePath":"\/Users\/aniavetian\/Desktop\/School Work\/UWB\/Masters\/CSS539\/ARShield\/ClickjackingTesting\/CJTest1.PNG","inferences":[{"classifications":[{"identifier":"clickjacking","confidence":0.9682409},{"identifier":"normal","confidence":0.03175909}],"coordinates":{"x":0.65087890625,"y":0.5791015625,"height":0.210693359375,"width":0.5361328125}}]}],"averagePrecision":{"normal":{"variedIoU":0,"IoU50":0},"clickjacking":{"IoU50":0.2916666666666667,"variedIoU":0.19166666666666665}},"meanAveragePrecision":{"IoU50":0.14583333333333334,"variedIoU":0.09583333333333333},"confusionMetrics":{"averagePrecision":{"IoU50":{"clickjacking":0.2916666666666667,"normal":0},"variedIoU":{"normal":0,"clickjacking":0.19166666666666665}},"meanAveragePrecision":{"variedIoU":0.09583333333333333,"IoU50":0.14583333333333334},"isValid":true}}},"analysedDataType":"datasource","createdDate":"2024-03-03T05:04:06Z","dataResult":{"dataSourceID":"4A3201E7-222C-4191-AA78-844D0461F88D","dataAnalysis":{"issues":[{"severity":"debug","description":"2 classes found, including clickjacking, normal"},{"severity":"warning","description":"Less than 50 total images found - add more to improve model validation"},{"severity":"debug","description":"Smallest class is \"normal\" with 2 images"},{"severity":"debug","description":"Largest class is \"clickjacking\" with 4 images"}],"classifierAnalysis":{"labelStats":{"clickjacking":4,"normal":2}},"summary":{"suggestedMaxIterations":1000,"classCount":2,"canUseValidation":0,"sampleCount":6,"counterExamples":0}},"createdDate":"2024-03-03T05:04:09Z","dataURL":"file:\/\/\/Users\/aniavetian\/Desktop\/School%20Work\/UWB\/Masters\/CSS539\/ARShield\/ClickjackingTesting\/","classesCount":2,"itemsCount":6},"startTime":"2024-03-03T05:04:11Z","dataSourceID":"4A3201E7-222C-4191-AA78-844D0461F88D","id":"4bdd8d73-ed68-4372-9442-8bab7d693e8e"}],"trainingEvaluationEntity":{"dataSourceID":"9A5C8A86-3DCE-4325-B076-16CEEDB300A8","id":"68cb1466-fb2d-44d7-8aae-aad094a961b8","dataResult":{"itemsCount":50,"dataAnalysis":{"summary":{"canUseValidation":1,"sampleCount":50,"counterExamples":0,"suggestedMaxIterations":2000,"classCount":2},"issues":[{"severity":"debug","description":"2 classes found, including clickjacking, normal"},{"severity":"good","description":"56 annotations found, automatically creating validation set"},{"description":"Smallest class is \"normal\" with 24 images","severity":"debug"},{"description":"Largest class is \"clickjacking\" with 32 images","severity":"debug"}],"classifierAnalysis":{"labelStats":{"normal":24,"clickjacking":32}}},"dataURL":"file:\/\/\/Users\/aniavetian\/Desktop\/School%20Work\/UWB\/Masters\/CSS539\/ARShield\/ClickjackingTraining\/","dataSourceID":"9A5C8A86-3DCE-4325-B076-16CEEDB300A8","classesCount":2,"createdDate":"2024-03-03T04:57:58Z"},"analysedDataType":"none","evaluationResult":{"objectDetector":{"meanAveragePrecision":{"variedIoU":0.0970027968287468,"IoU50":0.3648418188095093},"averagePrecision":{"clickjacking":{"IoU50":0.510581374168396,"variedIoU":0.13451364636421204},"normal":{"IoU50":0.21910226345062256,"variedIoU":0.059491951018571854}}}},"createdDate":"2024-03-03T04:57:58Z"}},"evaluationState":"evaluated","createdDate":"2024-03-03T04:57:58Z"}